argocd_csq/__init__.py
argocd_csq/auth_okta.py
argocd_csq/auth_type.py
argocd_csq/entrypoint_script.py
argocd_csq/login_type.py
argocd_csq/main.py
argocd_csq-0.2.2.dist-info/LICENSE
argocd_csq-0.2.2.dist-info/METADATA
argocd_csq-0.2.2.dist-info/WHEEL
argocd_csq-0.2.2.dist-info/entry_points.txt
argocd_csq-0.2.2.dist-info/top_level.txt
argocd_csq-0.2.2.dist-info/RECORD
